copyq_lib/__init__.py
copyq_lib/__main__.py
copyq_lib/cli.py
copyq_lib/core.py
copyq_lib/utils.py
copyq_lib-0.0.0.dist-info/AUTHORS.rst
copyq_lib-0.0.0.dist-info/LICENSE
copyq_lib-0.0.0.dist-info/METADATA
copyq_lib-0.0.0.dist-info/WHEEL
copyq_lib-0.0.0.dist-info/entry_points.txt
copyq_lib-0.0.0.dist-info/top_level.txt
copyq_lib-0.0.0.dist-info/RECORD
