Metadata-Version: 2.1
Name: copyq-lib
Version: 0.0.0
Summary: Collection of copyq functions
Home-page: https://github.com/weijia/python-copyq-lib
Author: Richard Wang
Author-email: richardwangwang@gmail.com
License: BSD-2-Clause
Project-URL: Documentation, https://python-copyq-lib.readthedocs.io/
Project-URL: Changelog, https://python-copyq-lib.readthedocs.io/en/latest/changelog.html
Project-URL: Issue Tracker, https://github.com/weijia/python-copyq-lib/issues
Classifier: Development Status :: 5 - Production/Stable
Classifier: Intended Audience :: Developers
Classifier: License :: OSI Approved :: BSD License
Classifier: Operating System :: Unix
Classifier: Operating System :: POSIX
Classifier: Operating System :: Microsoft :: Windows
Classifier: Programming Language :: Python
Classifier: Programming Language :: Python :: 3
Classifier: Programming Language :: Python :: 3 :: Only
Classifier: Programming Language :: Python :: 3.9
Classifier: Programming Language :: Python :: 3.10
Classifier: Programming Language :: Python :: 3.11
Classifier: Programming Language :: Python :: 3.12
Classifier: Programming Language :: Python :: Implementation :: CPython
Classifier: Programming Language :: Python :: Implementation :: PyPy
Classifier: Topic :: Utilities
Requires-Python: >=3.9
License-File: LICENSE
License-File: AUTHORS.rst
Requires-Dist: click
